odoo/addons/partner_company_group/README.rst
odoo/addons/partner_company_group/__init__.py
odoo/addons/partner_company_group/__manifest__.py
odoo/addons/partner_company_group/i18n/ca.po
odoo/addons/partner_company_group/i18n/es.po
odoo/addons/partner_company_group/i18n/it.po
odoo/addons/partner_company_group/i18n/partner_company_group.pot
odoo/addons/partner_company_group/i18n/pt_BR.po
odoo/addons/partner_company_group/i18n/zh_CN.po
odoo/addons/partner_company_group/readme/CONTRIBUTORS.md
odoo/addons/partner_company_group/readme/CREDITS.md
odoo/addons/partner_company_group/readme/DESCRIPTION.md
odoo/addons/partner_company_group/static/description/icon.png
odoo/addons/partner_company_group/static/description/index.html
odoo/addons/partner_company_group/views/account_move_views.xml
odoo/addons/partner_company_group/views/contact_view.xml
odoo/addons/partner_company_group/views/opportunity_view.xml
odoo/addons/partner_company_group/views/sale_order_view.xml
odoo_addon_partner_company_group-18.0.1.0.0.2.dist-info/METADATA
odoo_addon_partner_company_group-18.0.1.0.0.2.dist-info/WHEEL
odoo_addon_partner_company_group-18.0.1.0.0.2.dist-info/top_level.txt
odoo_addon_partner_company_group-18.0.1.0.0.2.dist-info/RECORD
